src/__init__.py
src/api.py
src/example.py
src/pagination_check.py
src/requests_handler.py
nws_api_check-1.0.2.dist-info/METADATA
nws_api_check-1.0.2.dist-info/WHEEL
nws_api_check-1.0.2.dist-info/licenses/LICENSE
nws_api_check-1.0.2.dist-info/RECORD
