Metadata-Version: 2.1
Name: NWS_API_check
Version: 1.0.2
Summary: Endpoint check for api.weather.gov
Author-email: Katie Grzybowski <katherine.dadamo@noaa.gov>
License-File: LICENSE
Classifier: License :: OSI Approved :: MIT License
Classifier: Operating System :: OS Independent
Classifier: Programming Language :: Python :: 3
Requires-Python: >=3.7
